examples/__init__.py
optichill/GBM_model.py
optichill/__init__.py
optichill/bas_filter.py
optichill/version.py
optichill/test/__init__.py
optichill/test/test_GBM_model.py
optichill/test/test_bas_filter.py
optichill-1.0.1.dist-info/METADATA
optichill-1.0.1.dist-info/RECORD
optichill-1.0.1.dist-info/WHEEL
optichill-1.0.1.dist-info/top_level.txt
